[
  {
    "tenant": "54c758b2aff1a55940d466a3",
    "name": "Master Class: Nail Art for Foot Fetishists",
    "loc": [
      30.497602,
      50.455775
    ],
    "tags": [
      "nails",
      "art"
    ],
    "description": "Decorate the nails of your loved ones. Turn the nails of your partner's toes into lovely rainbows.",
    "address": "02000 Kiev, Artema street 37-41, Staromak",
    "start": "2015-09-19T13:09:53Z",
    "picture": "https://img1.etsystatic.com/027/1/6849134/il_340x270.587612885_26gx.jpg",
    "achievements": [
      "Unicorns"
    ],
    "cookies": 1
  }
]